benchman/__init__.py
benchman/benchman.py
benchman/cli.py
benchman/cli_commands.py
benchman/context_info.py
benchman/dataset.py
benchman/py.typed
benchman/reporter.py
benchman/timings.py
benchman/util.py
benchman-0.0.1.dist-info/METADATA
benchman-0.0.1.dist-info/WHEEL
benchman-0.0.1.dist-info/entry_points.txt
benchman-0.0.1.dist-info/licenses/LICENSE
benchman-0.0.1.dist-info/RECORD
